AUTHORS
CHANGELOG.txt
DESCRIPTION
LICENSE
MANIFEST.in
README.rst
setup.cfg
setup.py
django_trello_freckle_sprints.egg-info/PKG-INFO
django_trello_freckle_sprints.egg-info/SOURCES.txt
django_trello_freckle_sprints.egg-info/dependency_links.txt
django_trello_freckle_sprints.egg-info/requires.txt
django_trello_freckle_sprints.egg-info/top_level.txt
sprints/__init__.py
sprints/admin.py
sprints/freckle_api.py
sprints/models.py
sprints/trello_api.py
sprints/urls.py
sprints/views.py
sprints/static/.empty
sprints/static/sprints/.empty
sprints/static/sprints/js/sprints.js
sprints/templates/sprints/.empty
sprints/templates/sprints/backlog_view.html
sprints/templates/sprints/home_view.html
sprints/templates/sprints/sprint_view.html
sprints/tests/__init__.py
sprints/tests/models_tests.py
sprints/tests/settings.py
sprints/tests/test_settings.py
sprints/tests/urls.py
sprints/tests/views_tests.py
sprints/tests/test_app/__init__.py
sprints/tests/test_app/models.py
sprints/tests/test_app/static/css/bootstrap.min.css
sprints/tests/test_app/static/js/bootstrap.min.js
sprints/tests/test_app/static/js/jquery-1.11.0.min.js
sprints/tests/test_app/templates/400.html
sprints/tests/test_app/templates/500.html
sprints/tests/test_app/templates/base.html