Metadata-Version: 1.0
Name: django-trello-freckle-sprints
Version: 0.1.1
Summary: A reusable Django app that creates burndown charts based on Trello boards and Freckle entries.
